{
  "total_rounds": 24,
  "total_cost": 4695.74,
  "platform_utility": -731.69,
  "remaining_budget": 304.26,
  "covered_task_count": 134,
  "trusted_count": 82,
  "init_select": 156,
  "later_select": 82,
  "trusted_workers_list": [
    "032",
    "095",
    "069",
    "074",
    "004",
    "139",
    "019",
    "021",
    "129",
    "128",
    "066",
    "123",
    "077",
    "100",
    "132",
    "078",
    "038",
    "002",
    "056",
    "063",
    "013",
    "131",
    "073",
    "106",
    "089",
    "081",
    "061",
    "045",
    "136",
    "098",
    "010",
    "018",
    "067",
    "020",
    "121",
    "005",
    "086",
    "076",
    "152",
    "054",
    "035",
    "091",
    "151",
    "048",
    "006",
    "084",
    "059",
    "044",
    "118",
    "070",
    "109",
    "141",
    "075",
    "143",
    "145",
    "153",
    "088",
    "022",
    "027",
    "012",
    "039",
    "082",
    "043",
    "037",
    "030",
    "116",
    "126",
    "112",
    "072",
    "101",
    "122",
    "060",
    "134",
    "007",
    "099",
    "154",
    "090",
    "042",
    "065",
    "080",
    "087",
    "120"
  ],
  "round_details": []
}