{
  "platform_utility": 3314.390000000001,
  "trusted_task_ratio": 0.6363636363636364,
  "total_rounds": 0,
  "total_cost": 1602.7000000000003,
  "remaining_budget": 8397.300000000001,
  "selected_workers": [],
  "init_select": 156,
  "later_select": 0,
  "covered_task_count": 176,
  "trusted_count": 93,
  "malicious_count": 47,
  "unknown_count": 16,
  "trusted_workers_list": [
    "013",
    "021",
    "109",
    "074",
    "106",
    "024",
    "006",
    "137",
    "011",
    "069",
    "066",
    "080",
    "124",
    "119",
    "076",
    "009",
    "146",
    "075",
    "095",
    "126",
    "001",
    "134",
    "103",
    "077",
    "084",
    "144",
    "039",
    "067",
    "044",
    "060",
    "081",
    "148",
    "152",
    "102",
    "003",
    "094",
    "093",
    "101",
    "054",
    "055",
    "036",
    "091",
    "079",
    "070",
    "072",
    "135",
    "012",
    "105",
    "098",
    "141",
    "088",
    "090",
    "118",
    "029",
    "082",
    "110",
    "065",
    "128",
    "059",
    "121",
    "133",
    "025",
    "155",
    "020",
    "149",
    "043",
    "117",
    "068",
    "140",
    "115",
    "145",
    "147",
    "042",
    "153",
    "142",
    "130",
    "022",
    "151",
    "064",
    "033",
    "034",
    "000",
    "138",
    "032",
    "023",
    "107",
    "087",
    "056",
    "143",
    "131",
    "040",
    "004",
    "018"
  ],
  "round_details": [
    {
      "round": 0,
      "trusted_count": 57,
      "unknown_count": 99,
      "malicious_count": 0,
      "recruited_workers": [
        "117",
        "083",
        "094"
      ]
    },
    {
      "round": 1,
      "trusted_count": 58,
      "unknown_count": 94,
      "malicious_count": 4,
      "recruited_workers": [
        "034",
        "125",
        "103",
        "079",
        "078",
        "144",
        "102"
      ]
    },
    {
      "round": 2,
      "trusted_count": 61,
      "unknown_count": 85,
      "malicious_count": 10,
      "recruited_workers": [
        "081",
        "010",
        "083",
        "064"
      ]
    },
    {
      "round": 3,
      "trusted_count": 61,
      "unknown_count": 84,
      "malicious_count": 11,
      "recruited_workers": [
        "084",
        "018"
      ]
    },
    {
      "round": 4,
      "trusted_count": 61,
      "unknown_count": 83,
      "malicious_count": 12,
      "recruited_workers": [
        "082",
        "140",
        "078",
        "147"
      ]
    },
    {
      "round": 5,
      "trusted_count": 64,
      "unknown_count": 75,
      "malicious_count": 17,
      "recruited_workers": [
        "063",
        "062",
        "053",
        "088",
        "008",
        "144",
        "147"
      ]
    },
    {
      "round": 6,
      "trusted_count": 67,
      "unknown_count": 70,
      "malicious_count": 19,
      "recruited_workers": [
        "145",
        "128",
        "013",
        "084",
        "004",
        "130",
        "124"
      ]
    },
    {
      "round": 7,
      "trusted_count": 71,
      "unknown_count": 64,
      "malicious_count": 21,
      "recruited_workers": [
        "145",
        "067",
        "047",
        "137",
        "044",
        "053",
        "084"
      ]
    },
    {
      "round": 8,
      "trusted_count": 73,
      "unknown_count": 59,
      "malicious_count": 24,
      "recruited_workers": [
        "026",
        "123",
        "044",
        "017",
        "068",
        "103",
        "004"
      ]
    },
    {
      "round": 9,
      "trusted_count": 75,
      "unknown_count": 55,
      "malicious_count": 26,
      "recruited_workers": [
        "050",
        "109",
        "067",
        "068",
        "106",
        "033",
        "031"
      ]
    },
    {
      "round": 10,
      "trusted_count": 75,
      "unknown_count": 52,
      "malicious_count": 29,
      "recruited_workers": [
        "050",
        "007",
        "037",
        "023",
        "131",
        "017",
        "119"
      ]
    },
    {
      "round": 11,
      "trusted_count": 76,
      "unknown_count": 50,
      "malicious_count": 30,
      "recruited_workers": [
        "023",
        "044",
        "024",
        "013",
        "140"
      ]
    },
    {
      "round": 12,
      "trusted_count": 78,
      "unknown_count": 45,
      "malicious_count": 33,
      "recruited_workers": [
        "108",
        "109",
        "067",
        "053",
        "011",
        "068",
        "144"
      ]
    },
    {
      "round": 13,
      "trusted_count": 79,
      "unknown_count": 44,
      "malicious_count": 33,
      "recruited_workers": [
        "122",
        "067",
        "023",
        "137",
        "040"
      ]
    },
    {
      "round": 14,
      "trusted_count": 81,
      "unknown_count": 37,
      "malicious_count": 38,
      "recruited_workers": [
        "077",
        "145",
        "016",
        "005",
        "115",
        "128",
        "023"
      ]
    },
    {
      "round": 15,
      "trusted_count": 84,
      "unknown_count": 27,
      "malicious_count": 45,
      "recruited_workers": [
        "022",
        "080",
        "005",
        "131",
        "139",
        "033",
        "103"
      ]
    },
    {
      "round": 16,
      "trusted_count": 87,
      "unknown_count": 22,
      "malicious_count": 47,
      "recruited_workers": [
        "142",
        "149",
        "080",
        "074",
        "126",
        "090",
        "140"
      ]
    },
    {
      "round": 17,
      "trusted_count": 87,
      "unknown_count": 22,
      "malicious_count": 47,
      "recruited_workers": [
        "006",
        "115",
        "076",
        "126",
        "094",
        "133",
        "018"
      ]
    },
    {
      "round": 18,
      "trusted_count": 89,
      "unknown_count": 20,
      "malicious_count": 47,
      "recruited_workers": [
        "077",
        "006",
        "095",
        "080",
        "099",
        "084"
      ]
    },
    {
      "round": 19,
      "trusted_count": 91,
      "unknown_count": 18,
      "malicious_count": 47,
      "recruited_workers": [
        "149",
        "065",
        "115",
        "074"
      ]
    },
    {
      "round": 20,
      "trusted_count": 91,
      "unknown_count": 18,
      "malicious_count": 47,
      "recruited_workers": [
        "071",
        "149",
        "080",
        "017",
        "105",
        "103",
        "144"
      ]
    },
    {
      "round": 21,
      "trusted_count": 91,
      "unknown_count": 18,
      "malicious_count": 47,
      "recruited_workers": [
        "096",
        "149",
        "128",
        "138",
        "088",
        "079",
        "135"
      ]
    },
    {
      "round": 22,
      "trusted_count": 93,
      "unknown_count": 16,
      "malicious_count": 47,
      "recruited_workers": [
        "006",
        "095",
        "126",
        "074",
        "084",
        "102",
        "143"
      ]
    },
    {
      "round": 23,
      "trusted_count": 93,
      "unknown_count": 16,
      "malicious_count": 47,
      "recruited_workers": [
        "006",
        "153",
        "084",
        "147"
      ]
    }
  ]
}